{"cameraMode":{"drawMode":0,"name":"Shaded","section":"Shading Mode"},"sceneLighting":true,"audioPlay":false,"sceneViewState":{"m_AlwaysRefresh":false,"showFog":true,"showSkybox":true,"showFlares":true,"showImageEffects":true,"showParticleSystems":true,"showVisualEffectGraphs":true,"m_FxEnabled":true},"in2DMode":false,"pivot":{"x":1.286294937133789,"y":7.144630432128906,"z":-5.357883453369141},"rotation":{"x":0.1481935828924179,"y":-0.8486970663070679,"z":0.31741708517074587,"w":0.39623329043388369},"size":12.547852516174317,"orthographic":false}